oldnews/__init__.py
oldnews/__main__.py
oldnews/commands/__init__.py
oldnews/commands/main.py
oldnews/data/__init__.py
oldnews/data/auth.py
oldnews/data/config.py
oldnews/data/db.py
oldnews/data/last_grab.py
oldnews/data/local_articles.py
oldnews/data/local_folders.py
oldnews/data/local_subscriptions.py
oldnews/data/local_unread.py
oldnews/data/locations.py
oldnews/data/navigation_state.py
oldnews/oldnews.py
oldnews/providers/__init__.py
oldnews/providers/main.py
oldnews/py.typed
oldnews/screens/__init__.py
oldnews/screens/login.py
oldnews/screens/main.py
oldnews/widgets/__init__.py
oldnews/widgets/article_content.py
oldnews/widgets/article_list.py
oldnews/widgets/navigation.py
oldnews-0.0.2.dist-info/WHEEL
oldnews-0.0.2.dist-info/entry_points.txt
oldnews-0.0.2.dist-info/METADATA
oldnews-0.0.2.dist-info/RECORD
