Metadata-Version: 2.4
Name: oldnews
Version: 0.0.2
Summary: A terminal-based client for TheOldReader
Keywords: atom,client,Google Reader,RSS,TheOldReader,terminal,news-reader,news
Author: Dave Pearson
Author-email: Dave Pearson <davep@davep.org>
License-Expression: GPL-3.0-or-later
Classifier: Development Status :: 3 - Alpha
Classifier: Operating System :: OS Independent
Classifier: Programming Language :: Python :: 3 :: Only
Classifier: Programming Language :: Python :: 3
Classifier: Programming Language :: Python :: 3.11
Classifier: Programming Language :: Python :: 3.12
Classifier: Programming Language :: Python :: 3.13
Classifier: Programming Language :: Python :: 3.14
Classifier: Typing :: Typed
Requires-Dist: html-to-markdown>=2.15.0
Requires-Dist: oldas>=0.3.1
Requires-Dist: textual>=6.3.0
Requires-Dist: textual-enhanced>=1.2.0
Requires-Dist: typedal>=4.2.2
Requires-Dist: xdg-base-dirs>=6.0.2
Requires-Python: >=3.11
Project-URL: Discussions, https://github.com/davep/oldnews/discussions
Project-URL: Documentation, https://oldnews.davep.dev/
Project-URL: Homepage, https://github.com/davep/oldnews
Project-URL: Issues, https://github.com/davep/oldnews/issues
Project-URL: Repository, https://github.com/davep/oldnews
Project-URL: Source, https://github.com/davep/oldnews
